pypacktest1/__init__.py
pypacktest1/module1.py
pypacktest1-0.1.0.dist-info/LICENSE
pypacktest1-0.1.0.dist-info/METADATA
pypacktest1-0.1.0.dist-info/WHEEL
pypacktest1-0.1.0.dist-info/top_level.txt
pypacktest1-0.1.0.dist-info/RECORD
